dna_analyzer/__init__.py
dna_analyzer/cpg_analyzer.py
dna_analyzer/sequence_analyzer.py
dna_analyzer/utils.py
tests/__init__.py
tests/test_analyzers.py
dna_analyzer-0.1.0.dist-info/METADATA
dna_analyzer-0.1.0.dist-info/WHEEL
dna_analyzer-0.1.0.dist-info/top_level.txt
dna_analyzer-0.1.0.dist-info/RECORD
