Metadata-Version: 2.1
Name: dna_analyzer
Version: 0.1.0
Summary: A package for DNA sequence analysis in cancer research
Home-page: https://github.com/yourusername/dna_analyzer
Author: Your Name
Author-email: your.email@example.com
Classifier: Programming Language :: Python :: 3
Classifier: License :: OSI Approved :: MIT License
Classifier: Operating System :: OS Independent
Classifier: Topic :: Scientific/Engineering :: Bio-Informatics
Requires-Python: >=3.8
Requires-Dist: biopython>=1.79
Requires-Dist: numpy>=1.21.0
Requires-Dist: pandas>=1.3.0
